MelodieTable/__init__.py
MelodieTable/reader_writer.py
MelodieTable/table_base.py
MelodieTable/table_general.py
MelodieTable/table_objects.py
MelodieTable/table_pyam.py
MelodieTable-0.3.0.dist-info/LICENSE
MelodieTable-0.3.0.dist-info/METADATA
MelodieTable-0.3.0.dist-info/WHEEL
MelodieTable-0.3.0.dist-info/entry_points.txt
MelodieTable-0.3.0.dist-info/top_level.txt
MelodieTable-0.3.0.dist-info/RECORD
